dependencytrack/__init__.py
dependencytrack/api.py
dependencytrack/project.py
gungnir-0.3.0.dist-info/LICENSE
gungnir-0.3.0.dist-info/METADATA
gungnir-0.3.0.dist-info/WHEEL
gungnir-0.3.0.dist-info/top_level.txt
gungnir-0.3.0.dist-info/RECORD
