Metadata-Version: 2.1
Name: gungnir
Version: 0.3.0
Summary: Homelab Automation Bot to Guard your very own Asgard
Author: GeekMasher
Project-URL: Homepage, https://github.com/GeekMasher/gungnir
Project-URL: Bug Tracker, https://github.com/GeekMasher/gungnir/issues
Classifier: Development Status :: 4 - Beta
Classifier: License :: OSI Approved :: MIT License
Classifier: Programming Language :: Python :: 3
Classifier: Programming Language :: Python :: 3.9
Classifier: Programming Language :: Python :: 3.10
Classifier: Programming Language :: Python :: 3.11
Classifier: Operating System :: OS Independent
Requires-Python: >=3.9
License-File: LICENSE
Requires-Dist: certifi ==2024.2.2
Requires-Dist: charset-normalizer ==3.3.2
Requires-Dist: docker ==7.0.0
Requires-Dist: idna ==3.7
Requires-Dist: packaging ==24.0
Requires-Dist: requests ==2.31.0
Requires-Dist: urllib3 ==2.2.1
Requires-Dist: websocket-client ==1.8.0
